{"_generic":{"defaultPackage":"systemstat","location":"","packages":{"systemstat":"0.1.10"},"sourcesAggregatedHash":null,"subsystem":"rust"},"_subsystem":{"gitSources":[],"relPathReplacements":{}},"cyclicDependencies":{},"decompressed":true,"dependencies":{"autocfg":{"1.0.1":[]},"bytesize":{"1.1.0":[{"name":"serde","version":"1.0.130"}]},"chrono":{"0.4.19":[{"name":"libc","version":"0.2.105"},{"name":"num-integer","version":"0.1.44"},{"name":"num-traits","version":"0.2.14"},{"name":"serde","version":"1.0.130"},{"name":"winapi","version":"0.3.9"}]},"lazy_static":{"1.4.0":[]},"libc":{"0.2.105":[]},"memchr":{"2.4.1":[]},"minimal-lexical":{"0.1.4":[]},"nom":{"7.0.0":[{"name":"memchr","version":"2.4.1"},{"name":"minimal-lexical","version":"0.1.4"},{"name":"version_check","version":"0.9.3"}]},"num-integer":{"0.1.44":[{"name":"autocfg","version":"1.0.1"},{"name":"num-traits","version":"0.2.14"}]},"num-traits":{"0.2.14":[{"name":"autocfg","version":"1.0.1"}]},"proc-macro2":{"1.0.30":[{"name":"unicode-xid","version":"0.2.2"}]},"quote":{"1.0.10":[{"name":"proc-macro2","version":"1.0.30"}]},"serde":{"1.0.130":[{"name":"serde_derive","version":"1.0.130"}]},"serde-feature-hack":{"0.2.0":[{"name":"serde","version":"1.0.130"}]},"serde_derive":{"1.0.130":[{"name":"proc-macro2","version":"1.0.30"},{"name":"quote","version":"1.0.10"},{"name":"syn","version":"1.0.80"}]},"syn":{"1.0.80":[{"name":"proc-macro2","version":"1.0.30"},{"name":"quote","version":"1.0.10"},{"name":"unicode-xid","version":"0.2.2"}]},"systemstat":{"0.1.10":[{"name":"bytesize","version":"1.1.0"},{"name":"chrono","version":"0.4.19"},{"name":"lazy_static","version":"1.4.0"},{"name":"libc","version":"0.2.105"},{"name":"nom","version":"7.0.0"},{"name":"serde-feature-hack","version":"0.2.0"},{"name":"winapi","version":"0.3.9"}]},"unicode-xid":{"0.2.2":[]},"version_check":{"0.9.3":[]},"winapi":{"0.3.9":[{"name":"winapi-i686-pc-windows-gnu","version":"0.4.0"},{"name":"winapi-x86_64-pc-windows-gnu","version":"0.4.0"}]},"winapi-i686-pc-windows-gnu":{"0.4.0":[]},"winapi-x86_64-pc-windows-gnu":{"0.4.0":[]}},"sources":{"autocfg":{"1.0.1":{"hash":"cdb031dd78e28731d87d56cc8ffef4a8f36ca26c38fe2de700543e627f8a464a","name":"autocfg","type":"crates-io","version":"1.0.1"}},"bytesize":{"1.1.0":{"hash":"6c58ec36aac5066d5ca17df51b3e70279f5670a72102f5752cb7e7c856adfc70","name":"bytesize","type":"crates-io","version":"1.1.0"}},"chrono":{"0.4.19":{"hash":"670ad68c9088c2a963aaa298cb369688cf3f9465ce5e2d4ca10e6e0098a1ce73","name":"chrono","type":"crates-io","version":"0.4.19"}},"lazy_static":{"1.4.0":{"hash":"e2abad23fbc42b3700f2f279844dc832adb2b2eb069b2df918f455c4e18cc646","name":"lazy_static","type":"crates-io","version":"1.4.0"}},"libc":{"0.2.105":{"hash":"869d572136620d55835903746bcb5cdc54cb2851fd0aeec53220b4bb65ef3013","name":"libc","type":"crates-io","version":"0.2.105"}},"memchr":{"2.4.1":{"hash":"308cc39be01b73d0d18f82a0e7b2a3df85245f84af96fdddc5d202d27e47b86a","name":"memchr","type":"crates-io","version":"2.4.1"}},"minimal-lexical":{"0.1.4":{"hash":"9c64630dcdd71f1a64c435f54885086a0de5d6a12d104d69b165fb7d5286d677","name":"minimal-lexical","type":"crates-io","version":"0.1.4"}},"nom":{"7.0.0":{"hash":"7ffd9d26838a953b4af82cbeb9f1592c6798916983959be223a7124e992742c1","name":"nom","type":"crates-io","version":"7.0.0"}},"num-integer":{"0.1.44":{"hash":"d2cc698a63b549a70bc047073d2949cce27cd1c7b0a4a862d08a8031bc2801db","name":"num-integer","type":"crates-io","version":"0.1.44"}},"num-traits":{"0.2.14":{"hash":"9a64b1ec5cda2586e284722486d802acf1f7dbdc623e2bfc57e65ca1cd099290","name":"num-traits","type":"crates-io","version":"0.2.14"}},"proc-macro2":{"1.0.30":{"hash":"edc3358ebc67bc8b7fa0c007f945b0b18226f78437d61bec735a9eb96b61ee70","name":"proc-macro2","type":"crates-io","version":"1.0.30"}},"quote":{"1.0.10":{"hash":"38bc8cc6a5f2e3655e0899c1b848643b2562f853f114bfec7be120678e3ace05","name":"quote","type":"crates-io","version":"1.0.10"}},"serde":{"1.0.130":{"hash":"f12d06de37cf59146fbdecab66aa99f9fe4f78722e3607577a5375d66bd0c913","name":"serde","type":"crates-io","version":"1.0.130"}},"serde-feature-hack":{"0.2.0":{"hash":"6ff5ff54f681a101d1a36cd5e4fe8b65eda3c9c5dafcdb2b9bbd7736f2381c71","name":"serde-feature-hack","type":"crates-io","version":"0.2.0"}},"serde_derive":{"1.0.130":{"hash":"d7bc1a1ab1961464eae040d96713baa5a724a8152c1222492465b54322ec508b","name":"serde_derive","type":"crates-io","version":"1.0.130"}},"syn":{"1.0.80":{"hash":"d010a1623fbd906d51d650a9916aaefc05ffa0e4053ff7fe601167f3e715d194","name":"syn","type":"crates-io","version":"1.0.80"}},"systemstat":{"0.1.10":{"hash":"sha256-iGKtsP1fTFcHsO62wux2EL16i/XgaRUL1t3gSn9A6/c=","type":"crates-io"}},"unicode-xid":{"0.2.2":{"hash":"8ccb82d61f80a663efe1f787a51b16b5a51e3314d6ac365b08639f52387b33f3","name":"unicode-xid","type":"crates-io","version":"0.2.2"}},"version_check":{"0.9.3":{"hash":"5fecdca9a5291cc2b8dcf7dc02453fee791a280f3743cb0905f8822ae463b3fe","name":"version_check","type":"crates-io","version":"0.9.3"}},"winapi":{"0.3.9":{"hash":"5c839a674fcd7a98952e593242ea400abe93992746761e38641405d28b00f419","name":"winapi","type":"crates-io","version":"0.3.9"}},"winapi-i686-pc-windows-gnu":{"0.4.0":{"hash":"ac3b87c63620426dd9b991e5ce0329eff545bccbbb34f3be09ff6fb6ab51b7b6","name":"winapi-i686-pc-windows-gnu","type":"crates-io","version":"0.4.0"}},"winapi-x86_64-pc-windows-gnu":{"0.4.0":{"hash":"712e227841d057c1ee1cd2fb22fa7e5a5461ae8e48fa2ca79ec42cfc1931183f","name":"winapi-x86_64-pc-windows-gnu","type":"crates-io","version":"0.4.0"}}}}