{
  "_generic": {
    "defaultPackage": "lock_api",
    "invalidationHash": "b13b8038c470c3d6dd120393e1b933159f6ea242153a4d8adcc1dc7994817db2",
    "location": "",
    "packages": {
      "lock_api": "0.4.7"
    },
    "sourcesAggregatedHash": null,
    "subsystem": "rust"
  },
  "_subsystem": {
    "gitSources": [],
    "relPathReplacements": {
      "lock_api": {
        "0.4.7": {}
      }
    }
  },
  "cyclicDependencies": {},
  "dependencies": {
    "lock_api": {
      "0.4.7": [
        [ "autocfg", "1.1.0" ],
        [ "owning_ref", "0.4.1" ],
        [ "scopeguard", "1.1.0" ],
        [ "serde", "1.0.140" ]
      ]
    },
    "owning_ref": {
      "0.4.1": [
        [ "stable_deref_trait", "1.2.0" ]
      ]
    }
  },
  "sources": {
    "autocfg": {
      "1.1.0": {
        "hash": "d468802bab17cbc0cc575e9b053f41e72aa36bfa6b7f55e3529ffa43161b97fa",
        "type": "crates-io"
      }
    },
    "lock_api": {
      "0.4.7": {
        "hash": "sha256-Mn+ltqaUDkaZ7Empvq4epIRca6uTFOT4SsaHQhOdjFM=",
        "pname": "lock_api",
        "type": "crates-io",
        "version": "0.4.7"
      }
    },
    "owning_ref": {
      "0.4.1": {
        "hash": "6ff55baddef9e4ad00f88b6c743a2a8062d4c6ade126c2a528644b8e444d52ce",
        "type": "crates-io"
      }
    },
    "scopeguard": {
      "1.1.0": {
        "hash": "d29ab0c6d3fc0ee92fe66e2d99f700eab17a8d57d1c1d3b748380fb20baa78cd",
        "type": "crates-io"
      }
    },
    "serde": {
      "1.0.140": {
        "hash": "fc855a42c7967b7c369eb5860f7164ef1f6f81c20c7cc1141f2a604e18723b03",
        "type": "crates-io"
      }
    },
    "stable_deref_trait": {
      "1.2.0": {
        "hash": "a8f112729512f8e442d81f95a8a7ddf2b7c6b8a1a6f509a95864142b30cab2d3",
        "type": "crates-io"
      }
    }
  }
}
