{
  "_generic": {
    "defaultPackage": "thiserror-impl",
    "invalidationHash": "7ba6d5fee3716d08a124d1edd7e5ca2def8691a7e8c628c1f6c67428aacdaca2",
    "location": "",
    "packages": {
      "thiserror-impl": "1.0.33"
    },
    "sourcesAggregatedHash": null,
    "subsystem": "rust"
  },
  "_subsystem": {
    "gitSources": [],
    "relPathReplacements": {
      "thiserror-impl": {
        "1.0.33": {}
      }
    }
  },
  "cyclicDependencies": {},
  "dependencies": {
    "proc-macro2": {
      "1.0.43": [
        [ "unicode-ident", "1.0.3" ]
      ]
    },
    "quote": {
      "1.0.21": [
        [ "proc-macro2", "1.0.43" ]
      ]
    },
    "syn": {
      "1.0.99": [
        [ "proc-macro2", "1.0.43" ],
        [ "quote", "1.0.21" ],
        [ "unicode-ident", "1.0.3" ]
      ]
    },
    "thiserror-impl": {
      "1.0.33": [
        [ "proc-macro2", "1.0.43" ],
        [ "quote", "1.0.21" ],
        [ "syn", "1.0.99" ]
      ]
    }
  },
  "sources": {
    "proc-macro2": {
      "1.0.43": {
        "hash": "0a2ca2c61bc9f3d74d2886294ab7b9853abd9c1ad903a3ac7815c58989bb7bab",
        "type": "crates-io"
      }
    },
    "quote": {
      "1.0.21": {
        "hash": "bbe448f377a7d6961e30f5955f9b8d106c3f5e449d493ee1b125c1d43c2b5179",
        "type": "crates-io"
      }
    },
    "syn": {
      "1.0.99": {
        "hash": "58dbef6ec655055e20b86b15a8cc6d439cca19b667537ac6a1369572d151ab13",
        "type": "crates-io"
      }
    },
    "thiserror-impl": {
      "1.0.33": {
        "hash": "sha256-wlHpD3COFsSaFvSRfcITHnUiK3Lt+py398WK5WquDAk=",
        "pname": "thiserror-impl",
        "type": "crates-io",
        "version": "1.0.33"
      }
    },
    "unicode-ident": {
      "1.0.3": {
        "hash": "c4f5b37a154999a8f3f98cc23a628d850e154479cd94decf3414696e12e31aaf",
        "type": "crates-io"
      }
    }
  }
}
