{
  "_generic": {
    "defaultPackage": "fuchsia-zircon-sys",
    "invalidationHash": "64bee4b2fd36b7200df45480db7e7bca609c6532969a5a27ad5fa104b83737a0",
    "location": "",
    "packages": {
      "fuchsia-zircon-sys": "0.3.3"
    },
    "sourcesAggregatedHash": null,
    "subsystem": "rust"
  },
  "_subsystem": {
    "gitSources": [],
    "relPathReplacements": {
      "fuchsia-zircon-sys": {
        "0.3.3": {}
      }
    }
  },
  "cyclicDependencies": {},
  "dependencies": {},
  "sources": {
    "fuchsia-zircon-sys": {
      "0.3.3": {
        "hash": "sha256-Pcqprncl0SzbhbOtmaQ023C0aMCd7RfgEthrXBAQ96c=",
        "pname": "fuchsia-zircon-sys",
        "type": "crates-io",
        "version": "0.3.3"
      }
    }
  }
}
