{
  "_generic": {
    "defaultPackage": "libc",
    "invalidationHash": "a199e00f83c11e303ccb4615f7bd380f9b7134184b6d68f67dc803e467e03edc",
    "location": "",
    "packages": {
      "libc": "0.2.134"
    },
    "sourcesAggregatedHash": null,
    "subsystem": "rust"
  },
  "_subsystem": {
    "gitSources": [],
    "relPathReplacements": {
      "libc": {
        "0.2.134": {}
      }
    }
  },
  "cyclicDependencies": {},
  "dependencies": {
    "libc": {
      "0.2.134": [
        [ "rustc-std-workspace-core", "1.0.0" ]
      ]
    }
  },
  "sources": {
    "libc": {
      "0.2.134": {
        "hash": "sha256-MpyTNUhza8Sf1XXuaMiei+TSYAZBhDiaW3dRfN3Zn/s=",
        "pname": "libc",
        "type": "crates-io",
        "version": "0.2.134"
      }
    },
    "rustc-std-workspace-core": {
      "1.0.0": {
        "hash": "1956f5517128a2b6f23ab2dadf1a976f4f5b27962e7724c2bf3d45e539ec098c",
        "type": "crates-io"
      }
    }
  }
}
